buildbot_netauth/__init__.py
buildbot_netauth-0.1.1.dist-info/LICENSE
buildbot_netauth-0.1.1.dist-info/METADATA
buildbot_netauth-0.1.1.dist-info/WHEEL
buildbot_netauth-0.1.1.dist-info/entry_points.txt
buildbot_netauth-0.1.1.dist-info/top_level.txt
buildbot_netauth-0.1.1.dist-info/RECORD
