Metadata-Version: 2.1
Name: buildbot-netauth
Version: 0.1.1
Summary: buildbot plugin for integration with NetAuth
Author-email: classabbyamp <dev@placeviolette.net>
Project-URL: Repository, https://github.com/classabbyamp/buildbot-netauth
Project-URL: Changelog, https://github.com/classabbyamp/buildbot-netauth/blob/master/CHANGELOG.md
Keywords: secure-access,authentication-service,netauth,buildbot
Classifier: License :: OSI Approved :: MIT License
Classifier: Programming Language :: Python :: 3
Classifier: Programming Language :: Python :: 3.11
Classifier: Programming Language :: Python :: 3.12
Requires-Python: >=3.11
License-File: LICENSE
Requires-Dist: netauth
Requires-Dist: buildbot~=4.0
Provides-Extra: ci
Requires-Dist: ruff; extra == "ci"
